oopmultilang/__init__.py
oopmultilang/_errors.py
oopmultilang/_lang_dict_parser.py
oopmultilang/lang_switcher.py
oopmultilang-1.0.1.dist-info/LICENSE
oopmultilang-1.0.1.dist-info/METADATA
oopmultilang-1.0.1.dist-info/WHEEL
oopmultilang-1.0.1.dist-info/RECORD
