Metadata-Version: 2.1
Name: oopmultilang
Version: 1.0.1
Summary: A Python package that supports multi-language conversion of the object-oriented paradigm.
Home-page: https://github.com/leoweyr/Python-OOPMultilang
License: MIT
Author: leoweyr
Author-email: leoweyr@foxmail.com
Requires-Python: >=3.8,<4.0
Classifier: Development Status :: 3 - Alpha
Classifier: License :: OSI Approved :: MIT License
Classifier: Programming Language :: Python :: 3
Classifier: Programming Language :: Python :: 3.8
Classifier: Programming Language :: Python :: 3.9
Classifier: Programming Language :: Python :: 3.10
Classifier: Programming Language :: Python :: 3.11
Requires-Dist: easierfile (>=3.0.0,<4.0.0)
Project-URL: Repository, https://github.com/leoweyr/Python-OOPMultilang
